Nlimits/__init__.py
Nlimits/hnl_tools.py
Nlimits/plot_tools.py
Nlimits/plotter.py
Heavy_Neutrino_Limits-0.0.2.dist-info/LICENSE
Heavy_Neutrino_Limits-0.0.2.dist-info/METADATA
Heavy_Neutrino_Limits-0.0.2.dist-info/WHEEL
Heavy_Neutrino_Limits-0.0.2.dist-info/top_level.txt
Heavy_Neutrino_Limits-0.0.2.dist-info/RECORD
